niteco/__init__.py
niteco/opal_rest_tool/__init__.py
niteco/opal_rest_tool/openapi_parser.py
niteco/opal_rest_tool/rest_handler.py
niteco/opal_rest_tool/rest_models.py
niteco/opal_rest_tool/rest_tool_service.py
niteco_opal_rest_tool-0.1.7.dist-info/METADATA
niteco_opal_rest_tool-0.1.7.dist-info/WHEEL
niteco_opal_rest_tool-0.1.7.dist-info/top_level.txt
niteco_opal_rest_tool-0.1.7.dist-info/RECORD
