Metadata-Version: 2.4
Name: niteco.opal-rest-tool
Version: 0.1.7
Summary: OPAL REST Tool Service - Automatically generates tools from OpenAPI 3.x specifications
Author-email: Niteco <info@niteco.com>
License-Expression: MIT
Project-URL: Homepage, https://github.com/niteco/opal-rest-tool
Project-URL: Repository, https://github.com/niteco/opal-rest-tool
Project-URL: Documentation, https://github.com/niteco/opal-rest-tool#readme
Project-URL: Issues, https://github.com/niteco/opal-rest-tool/issues
Keywords: openapi,rest,api,tools,opal,fastapi
Classifier: Development Status :: 4 - Beta
Classifier: Intended Audience :: Developers
Classifier: Programming Language :: Python :: 3
Classifier: Programming Language :: Python :: 3.8
Classifier: Programming Language :: Python :: 3.9
Classifier: Programming Language :: Python :: 3.10
Classifier: Programming Language :: Python :: 3.11
Classifier: Programming Language :: Python :: 3.12
Classifier: Topic :: Software Development :: Libraries :: Python Modules
Classifier: Topic :: Internet :: WWW/HTTP :: HTTP Servers
Classifier: Topic :: Software Development :: Code Generators
Requires-Python: >=3.8
Requires-Dist: optimizely-opal.opal-tools-sdk>=0.1.4.dev0
Requires-Dist: fastapi>=0.116.0
Requires-Dist: httpx>=0.28.0
Requires-Dist: pyyaml>=6.0.0
Requires-Dist: pydantic>=2.11.0
Requires-Dist: uvicorn[standard]>=0.35.0
Provides-Extra: dev
Requires-Dist: pytest>=7.0.0; extra == "dev"
Requires-Dist: pytest-asyncio>=0.21.0; extra == "dev"
Requires-Dist: black>=23.0.0; extra == "dev"
Requires-Dist: isort>=5.12.0; extra == "dev"
Requires-Dist: mypy>=1.0.0; extra == "dev"
